schema_agents/__init__.py
schema_agents/config.py
schema_agents/const.py
schema_agents/llm.py
schema_agents/logs.py
schema_agents/role.py
schema_agents/schema.py
schema_agents/memory/__init__.py
schema_agents/memory/base_store.py
schema_agents/memory/faiss_store.py
schema_agents/memory/long_term_memory.py
schema_agents/memory/memory.py
schema_agents/provider/__init__.py
schema_agents/provider/base_chatbot.py
schema_agents/provider/base_gpt_api.py
schema_agents/provider/openai_api.py
schema_agents/teams/__init__.py
schema_agents/teams/databse_explore_hub/__init__.py
schema_agents/teams/databse_explore_hub/database_explorer.py
schema_agents/teams/image_analysis_hub/__init__.py
schema_agents/teams/image_analysis_hub/data_engineer.py
schema_agents/teams/image_analysis_hub/microscopist.py
schema_agents/teams/image_analysis_hub/schemas.py
schema_agents/teams/image_analysis_hub/web_developer.py
schema_agents/tools/__init__.py
schema_agents/tools/binder.py
schema_agents/tools/code_interpreter.py
schema_agents/tools/msgspec_v5.py
schema_agents/tools/ray_utils.py
schema_agents/utils/__init__.py
schema_agents/utils/common.py
schema_agents/utils/mermaid.py
schema_agents/utils/schema_conversion.py
schema_agents/utils/serialize.py
schema_agents/utils/singleton.py
schema_agents/utils/token_counter.py
schema_agents-0.1.62.dist-info/METADATA
schema_agents-0.1.62.dist-info/WHEEL
schema_agents-0.1.62.dist-info/top_level.txt
schema_agents-0.1.62.dist-info/RECORD
