Metadata-Version: 2.1
Name: schema-agents
Version: 0.1.62
Summary: A schema-based LLM framework for building multi-agent collaborative systems.
Requires-Dist: numpy>=1.21.2
Requires-Dist: jsonschema>=4.0.1
Requires-Dist: shortuuid>=1.0.1
Requires-Dist: pydantic>=2.6.1
Requires-Dist: openai>=1.31.0
Requires-Dist: loguru
Requires-Dist: jupyter-client
Requires-Dist: faiss-cpu
Requires-Dist: pyyaml
Requires-Dist: tiktoken>=0.7.0
Requires-Dist: tenacity
Requires-Dist: openapi-pydantic
Requires-Dist: makefun>=1.15.2
Requires-Dist: langchain>=0.1.10
Requires-Dist: langchain-community>=0.0.25
